knx_ga_exporter-2.0.2.dist-info/METADATA
knx_ga_exporter-2.0.2.dist-info/WHEEL
knx_ga_exporter-2.0.2.dist-info/entry_points.txt
knx_ga_exporter-2.0.2.dist-info/licenses/LICENSE
knx_ga_exporter/CHANGELOG.md
knx_ga_exporter/__init__.py
knx_ga_exporter/__main__.py
knx_ga_exporter/argparse.py
knx_ga_exporter/exporter.py
knx_ga_exporter/group_address.py
knx_ga_exporter/logging.py
knx_ga_exporter/parser.py
knx_ga_exporter-2.0.2.dist-info/RECORD
