Metadata-Version: 2.1
Name: knx-ga-exporter
Version: 2.0.2
Summary: Converter for spreadsheets to KNX ETS group address configurations in CSV format.
Author-Email: Sebastian Waldvogel <sebastian@waldvogels.de>
License: MIT
Project-URL: Repository, https://github.com/waldbaer/knx-ga-exporter
Requires-Python: >=3.9
Requires-Dist: openpyxl==3.1.5
Requires-Dist: jsonargparse==4.40.1
Requires-Dist: rich-argparse==1.7.1
